provesid/__init__.py
provesid/cache.py
provesid/cascommonchem.py
provesid/chebi.py
provesid/classyfire.py
provesid/opsin.py
provesid/pubchem.py
provesid/pubchemview.py
provesid/resolver.py
provesid/tools.py
provesid/utils.py
provesid/data/commonchemistry-swagger.json
provesid-0.2.0.dist-info/licenses/LICENSE
provesid-0.2.0.dist-info/METADATA
provesid-0.2.0.dist-info/WHEEL
provesid-0.2.0.dist-info/top_level.txt
provesid-0.2.0.dist-info/RECORD
