Metadata-Version: 2.4
Name: provesid
Version: 0.2.0
Summary: A Python package for chemical identifier resolution and experimental property extraction
Author-email: "Ali A. Eftekhari and USEtox team" <e.eftekhari@gmail.com>
License: MIT
Project-URL: Homepage, https://github.com/USEtox/PROVESID
Project-URL: Documentation, https://usetox.github.io/PROVESID/
Project-URL: Repository, https://github.com/USEtox/PROVESID
Project-URL: Bug Tracker, https://github.com/USEtox/PROVESID/issues
Keywords: chemistry,cheminformatics,pubchem,chemical-identifiers,api
Classifier: Development Status :: 4 - Beta
Classifier: Intended Audience :: Science/Research
Classifier: Operating System :: OS Independent
Classifier: Programming Language :: Python :: 3
Classifier: Programming Language :: Python :: 3.8
Classifier: Programming Language :: Python :: 3.9
Classifier: Programming Language :: Python :: 3.10
Classifier: Programming Language :: Python :: 3.11
Classifier: Topic :: Scientific/Engineering :: Chemistry
Classifier: Topic :: Software Development :: Libraries :: Python Modules
Requires-Python: >=3.8
License-File: LICENSE
Requires-Dist: requests>=2.25.0
Requires-Dist: pandas>=1.3.0
Requires-Dist: numpy>=1.21.0
Requires-Dist: tqdm>=4.60.0
Provides-Extra: dev
Requires-Dist: pytest>=6.0; extra == "dev"
Requires-Dist: black>=21.0; extra == "dev"
Requires-Dist: flake8>=3.8; extra == "dev"
Requires-Dist: mkdocs>=1.4; extra == "dev"
Requires-Dist: mkdocs-material>=8.0; extra == "dev"
Requires-Dist: mkdocstrings[python]>=0.19; extra == "dev"
Provides-Extra: test
Requires-Dist: pytest>=6.0; extra == "test"
Requires-Dist: pytest-cov>=2.0; extra == "test"
Requires-Dist: pytest-xdist>=2.0; extra == "test"
Requires-Dist: pytest-mock>=3.0; extra == "test"
Requires-Dist: pytest-timeout>=2.0; extra == "test"
Provides-Extra: docs
Requires-Dist: mkdocs>=1.4; extra == "docs"
Requires-Dist: mkdocs-material>=8.0; extra == "docs"
Requires-Dist: mkdocstrings[python]>=0.19; extra == "docs"
Requires-Dist: mkdocs-jupyter>=0.24.0; extra == "docs"
Requires-Dist: mkdocs-autorefs>=0.4.0; extra == "docs"
Provides-Extra: chemistry
Requires-Dist: rdkit-pypi>=2022.09.0; extra == "chemistry"
Dynamic: license-file
